vibex_sh/__init__.py
vibex_sh/client.py
vibex_sh/config.py
vibex_sh/handler.py
vibex_sh/normalize.py
vibex_sh-1.0.0.dist-info/METADATA
vibex_sh-1.0.0.dist-info/WHEEL
vibex_sh-1.0.0.dist-info/top_level.txt
vibex_sh-1.0.0.dist-info/RECORD
